haokan_download/__init__.py
haokan_download/__main__.py
haokan_download/config.py
haokan_download/download_help.py
haokan_download/haokan_author.py
haokan_download/main.py
haokan_download/cache/__init__.py
haokan_download/cache/cache_interface.py
haokan_download/cache/cache_manager.py
haokan_download/cache/file_cache.py
haokan_download/cache/none_cache.py
haokan_download_icexmoon-0.0.3.dist-info/LICENSE
haokan_download_icexmoon-0.0.3.dist-info/METADATA
haokan_download_icexmoon-0.0.3.dist-info/WHEEL
haokan_download_icexmoon-0.0.3.dist-info/entry_points.txt
haokan_download_icexmoon-0.0.3.dist-info/top_level.txt
haokan_download_icexmoon-0.0.3.dist-info/RECORD
