Metadata-Version: 2.1
Name: haokan-download-icexmoon
Version: 0.0.3
Summary: auto download one authors video on haokan website
Home-page: https://github.com/icexmoon/haokan-download
Author: icexmoon
Author-email: icexmoon@qq.com
Project-URL: Bug Tracker, https://github.com/icexmoon/haokan-download/issues
Classifier: Programming Language :: Python :: 3
Classifier: License :: OSI Approved :: MIT License
Classifier: Operating System :: OS Independent
Requires-Python: >=3.6
License-File: LICENSE
Requires-Dist: requests
Requires-Dist: beautifulsoup4
Requires-Dist: html5lib
Requires-Dist: you-get
Requires-Dist: jsonlines
